{
  "project_info": {
    "project_number": "328744831606",
    "project_id": "ytdopamine",
    "storage_bucket": "ytdopamine.appspot.com"
  },
  "client": [
    {
      "client_info": {
        "mobilesdk_app_id": "1:328744831606:android:6f646b1e0b3bd3a5c76d57",
        "android_client_info": {
          "package_name": "com.google.android.piyush.dopamine"
        }
      },
      "oauth_client": [
        {
          "client_id": "328744831606-dldmp8lfg2dm1at09fjs6836gr05ngjl.apps.googleusercontent.com",
          "client_type": 1,
          "android_info": {
            "package_name": "com.google.android.piyush.dopamine",
            "certificate_hash": "e3e3e66d36b9be65e2e5015ac48a454150a05afe"
          }
        },
        {
          "client_id": "328744831606-g4gees2nj81o498p6s88n69s3ra4abb1.apps.googleusercontent.com",
          "client_type": 3
        }
      ],
      "api_key": [
        {
          "current_key": "AIzaSyAP3fC_Js5LABEj0w0ZqbuqQq-k7HdaA0s"
        }
      ],
      "services": {
        "appinvite_service": {
          "other_platform_oauth_client": [
            {
              "client_id": "328744831606-g4gees2nj81o498p6s88n69s3ra4abb1.apps.googleusercontent.com",
              "client_type": 3
            }
          ]
        }
      }
    }
  ],
  "configuration_version": "1"
}